{"date":"2019-11-06T13:33:23.218Z","venue":{"name":"AlexanderPlatz","address":"Alex 24","sports":[{"type":"team","minAttendee":6},{"type":"individual","minAttendee":1}]},"maxNumber":6,"sport":{"type":"individual","minAttendee":1},"waitingList":[],"participants":[{"id":1,"firstName":"alina","secondName":"nasti","email":"alina.ghe@gmail.com","sports":[{"type":"individual","minAttendee":1}]},{"id":2,"firstName":"aurel","secondName":"nasti","email":"aurel.ghe@gmail.com","sports":[{"type":"individual","minAttendee":1}]}]}